fompy/__init__.py
fompy/aux.py
fompy/conditioning.py
fompy/fds.py
fompy/fom.py
fompy/plots.py
fompy/wrappers.py
fompy-0.3.8.dist-info/LICENSE.rst
fompy-0.3.8.dist-info/METADATA
fompy-0.3.8.dist-info/WHEEL
fompy-0.3.8.dist-info/top_level.txt
fompy-0.3.8.dist-info/RECORD
