Metadata-Version: 2.1
Name: fompy
Version: 0.3.8
Summary: FoMPy is an effective tool that extracts the main figures of merit (FoM) of a semiconductors IV curve
Home-page: https://gitlab.citius.usc.es/gabriel.espineira/FoMPy
Author: Gabriel Espineira
Author-email: gabrielespineiradeus@gmail.com
License: MIT
Platform: UNKNOWN
Classifier: Topic :: Utilities
Classifier: Intended Audience :: Developers
Classifier: Intended Audience :: Information Technology
Classifier: License :: OSI Approved :: MIT License
Classifier: Operating System :: Unix
Classifier: Programming Language :: Python :: 3
Requires-Dist: scipy
Requires-Dist: pytest
Requires-Dist: probscale
Requires-Dist: matplotlib
